navio_jupyter/__init__.py
navio_jupyter/static/widget.css
navio_jupyter/static/widget.js
navio_jupyter-0.3.0.dist-info/METADATA
navio_jupyter-0.3.0.dist-info/WHEEL
navio_jupyter-0.3.0.dist-info/RECORD
