Metadata-Version: 2.3
Name: navio_jupyter
Version: 0.3.0
Requires-Dist: anywidget
Provides-Extra: dev
Requires-Dist: jupyterlab; extra == 'dev'
Requires-Dist: watchfiles; extra == 'dev'
